{
    "org": "Santa Ana",
    "dest": "Texas",
    "days": 7,
    "visiting city number": 3,
    "date": [
        "2022-03-25",
        "2022-03-26",
        "2022-03-27",
        "2022-03-28",
        "2022-03-29",
        "2022-03-30",
        "2022-03-31"
    ],
    "people_number": 4,
    "house rule": "children under 10",
    "cuisine": null,
    "room type": null,
    "transportation": null,
    "budget": 5800,
    "query": "We need a 7-day travel plan for a group of 4, taking off from Santa Ana and visiting 3 different cities in Texas from March 25th to March 31st, 2022. Our budget is set at $5,800 for the trip. Additionally, our lodging options must accommodate children under the age of 10.",
    "level": "middle",
    "annotated plan": [
        {
            "days": 1,
            "current_city": "from Santa Ana to Abilene(Texas)",
            "transportation": "Self-driving, from Santa Ana to Abilene(Texas), duration: 18 hours 0 mins, distance: 1,995 km, cost: 99",
            "breakfast": "-",
            "attraction": "-",
            "lunch": "-",
            "dinner": "Dilli Darbar, Abilene(Texas)",
            "accommodation": "Cozy Artists Apartment in Central Harlem, Abilene(Texas)"
        },
        {
            "days": 2,
            "current_city": "Abilene(Texas)",
            "transportation": "-",
            "breakfast": "Biryani Express, Abilene(Texas)",
            "attraction": "Frontier Texas!, Abilene(Texas);Historic Fort Phantom Hill, Abilene(Texas);12th Armored Division Memorial, Abilene(Texas);National Center for Children's Illustrated Literature, Abilene(Texas);",
            "lunch": "Gelato Vinto, Abilene(Texas)",
            "dinner": "Thai Garden, Abilene(Texas)",
            "accommodation": "Cozy Artists Apartment in Central Harlem, Abilene(Texas)"
        },
        {
            "days": 3,
            "current_city": "from Abilene(Texas) to Amarillo(Texas)",
            "transportation": "Self-driving, from Abilene(Texas) to Amarillo(Texas), duration: 4 hours 9 mins, distance: 446 km, cost: 22",
            "breakfast": "Inam Muradabadi, Abilene(Texas)",
            "attraction": "Amarillo Botanical Gardens, Amarillo(Texas);Cadillac Ranch, Amarillo(Texas);",
            "lunch": "-",
            "dinner": "U Like, Amarillo(Texas)",
            "accommodation": "1BR Doorman Bldg Boerum Hill BK, Amarillo(Texas)"
        },
        {
            "days": 4,
            "current_city": "Amarillo(Texas)",
            "transportation": "-",
            "breakfast": "Wood Box Cafe, Amarillo(Texas)",
            "attraction": "Amarillo Zoo, Amarillo(Texas);Don Harrington Discovery Center, Amarillo(Texas);Texas Air & Space Museum, Amarillo(Texas);",
            "lunch": "Biryani Sons & Co., Amarillo(Texas)",
            "dinner": "Sugar Daddy Bakers, Amarillo(Texas)",
            "accommodation": "1BR Doorman Bldg Boerum Hill BK, Amarillo(Texas)"
        },
        {
            "days": 5,
            "current_city": "from Amarillo(Texas) to Lubbock(Texas)",
            "transportation": "Self-driving, from Amarillo(Texas) to Lubbock(Texas), duration: 1 hour 47 mins, distance: 197 km, cost: 9",
            "breakfast": "The Cinnamon Kitchen, Amarillo(Texas)",
            "attraction": "Buddy Holly Center, Lubbock(Texas);",
            "lunch": "-",
            "dinner": "Keventers, Lubbock(Texas)",
            "accommodation": "Gorgeous Spacious Room in Clinton Hill, Lubbock(Texas)"
        },
        {
            "days": 6,
            "current_city": "Lubbock(Texas)",
            "transportation": "-",
            "breakfast": "Handi, Lubbock(Texas)",
            "attraction": "American Windmill Museum, Lubbock(Texas);Mackenzie Main City Park, Lubbock(Texas);Museum of Texas Tech University, Lubbock(Texas);Prairie Dog Town, Lubbock(Texas);",
            "lunch": "Punjabi Chaap Corner, Lubbock(Texas)",
            "dinner": "Grand Barbeque Buffet Restaurant, Lubbock(Texas)",
            "accommodation": "Gorgeous Spacious Room in Clinton Hill, Lubbock(Texas)"
        },
        {
            "days": 7,
            "current_city": "from Lubbock(Texas) to Santa Ana",
            "transportation": "Self-driving, from Lubbock(Texas) to Santa Ana, duration: 16 hours 25 mins, distance: 1,777 km, cost: 88",
            "breakfast": "Paris 6 Classique, Lubbock(Texas)",
            "attraction": "-",
            "lunch": "-",
            "dinner": "-",
            "accommodation": "-"
        }
    ]
}